project201/bmitest2.py
project201-0.0.0.2.dist-info/METADATA
project201-0.0.0.2.dist-info/WHEEL
project201-0.0.0.2.dist-info/top_level.txt
project201-0.0.0.2.dist-info/RECORD
