Metadata-Version: 2.1
Name: project201
Version: 0.0.0.2
Summary: My First Test Package
Home-page: UNKNOWN
Author: Kuksung
Author-email: gamsic12@gmail.com
License: MIT
Platform: UNKNOWN
Requires-Python: >=3
